table_format/__init__.py
table_format/__main__.py
table_format/api.py
table_format/cli.py
table_format/version.py
table_format-1.4.2.dist-info/LICENSE
table_format-1.4.2.dist-info/METADATA
table_format-1.4.2.dist-info/WHEEL
table_format-1.4.2.dist-info/entry_points.txt
table_format-1.4.2.dist-info/top_level.txt
table_format-1.4.2.dist-info/RECORD
