Metadata-Version: 2.1
Name: table-format
Version: 1.4.2
Summary: Format Python code (list of lists) as a fixed width table.
Home-page: https://github.com/spookylukey/table-format
Author: Luke Plant
Author-email: L.Plant.98@cantab.net
Maintainer: Luke Plant
Maintainer-email: L.Plant.98@cantab.net
License: MIT
Download-URL: https://github.com/spookylukey/table-format/releases
Project-URL: Bug Tracker, https://github.com/spookylukey/table-format/issues
Project-URL: Source Code, https://github.com/spookylukey/table-format
Keywords: table,format,fixed-width,columns
Platform: UNKNOWN
Classifier: Development Status :: 4 - Beta
Classifier: Environment :: Console
Classifier: Intended Audience :: Developers
Classifier: License :: OSI Approved :: MIT License
Classifier: Operating System :: OS Independent
Classifier: Framework :: Pytest
Classifier: Framework :: tox
Classifier: Programming Language :: Python
Classifier: Programming Language :: Python :: 3.8
Classifier: Programming Language :: Python :: 3.9
Classifier: Programming Language :: Python :: 3.10
Classifier: Programming Language :: Python :: 3 :: Only
Classifier: Topic :: Software Development
Requires-Python: >=3.8
License-File: LICENSE
Requires-Dist: libcst
Requires-Dist: ast-decompiler
Requires-Dist: parsy
Provides-Extra: tests
Requires-Dist: pytest ; extra == 'tests'
